structure_inspector/__init__.py
structure_inspector/structure_inspector.py
structure_inspector-1.0.5.dist-info/LICENSE
structure_inspector-1.0.5.dist-info/METADATA
structure_inspector-1.0.5.dist-info/WHEEL
structure_inspector-1.0.5.dist-info/top_level.txt
structure_inspector-1.0.5.dist-info/RECORD
