Metadata-Version: 2.1
Name: structure-inspector
Version: 1.0.5
Summary: A Python package to print the structure of complex, nested Python objects.
Home-page: https://github.com/everyai/structure_inspector
Author: Every AI LLC
Author-email: opensource@everyai.llc
Classifier: Programming Language :: Python :: 3
Classifier: License :: OSI Approved :: MIT License
Classifier: Operating System :: OS Independent
Requires-Python: >=3.6
License-File: LICENSE
